AUTHORS.rst
CONTRIBUTING.rst
HISTORY.rst
LICENSE
MANIFEST.in
README.rst
setup.py
pyrobot/__init__.py
pyrobot/browser.py
pyrobot/compat.py
pyrobot/helpers.py
pyrobot/ordereddict.py
pyrobot/responses.py
pyrobot.egg-info/PKG-INFO
pyrobot.egg-info/SOURCES.txt
pyrobot.egg-info/dependency_links.txt
pyrobot.egg-info/not-zip-safe
pyrobot.egg-info/requires.txt
pyrobot.egg-info/top_level.txt