Metadata-Version: 1.1
Name: pyrobot
Version: 0.1.0
Summary: Your friendly neighborhood web scraper
Home-page: https://github.com/jmcarp/pyrobot
Author: Joshua Carp
Author-email: jm.carp@gmail.com
License: MIT
Keywords: pyrobot
Platform: UNKNOWN
Classifier: Development Status :: 2 - Pre-Alpha
Classifier: Intended Audience :: Developers
Classifier: License :: OSI Approved :: BSD License
Classifier: Natural Language :: English
Classifier: Programming Language :: Python :: 2
Classifier: Programming Language :: Python :: 2.6
Classifier: Programming Language :: Python :: 2.7
Classifier: Programming Language :: Python :: 3
Classifier: Programming Language :: Python :: 3.3
